dame_flame/__init__.py
dame_flame/dame_algorithm.py
dame_flame/data_cleaning.py
dame_flame/early_stops.py
dame_flame/flame_algorithm.py
dame_flame/flame_dame_helpers.py
dame_flame/flame_group_by.py
dame_flame/generate_new_active_sets.py
dame_flame/grouped_mr.py
dame_flame/matching.py
dame_flame/utils/__init__.py
dame_flame/utils/data.py
dame_flame/utils/post_processing.py
dame_flame-0.81.dist-info/licenses/LICENSE.txt
dame_flame-0.81.dist-info/METADATA
dame_flame-0.81.dist-info/WHEEL
dame_flame-0.81.dist-info/top_level.txt
dame_flame-0.81.dist-info/RECORD
