Metadata-Version: 2.4
Name: dame_flame
Version: 0.81
Summary: Causal Inference Covariate Matching
Home-page: https://github.com/almost-matching-exactly/DAME-FLAME-Python-Package
Author: Neha R. Gupta
Author-email: nehargupta@cmu.edu
License: MIT
Keywords: Causal Inference Matching Econometrics Data Machine Learning FLAME DAME Causality ML
Classifier: Programming Language :: Python :: 3
Classifier: License :: OSI Approved :: MIT License
Classifier: Operating System :: OS Independent
Requires-Python: >=3.6
License-File: LICENSE.txt
Requires-Dist: scikit-learn>=0.23.2
Requires-Dist: scipy>=0.14
Requires-Dist: pandas>=0.11.0
Requires-Dist: numpy>=1.16.5
Dynamic: author
Dynamic: author-email
Dynamic: classifier
Dynamic: description
Dynamic: description-content-type
Dynamic: home-page
Dynamic: keywords
Dynamic: license
Dynamic: license-file
Dynamic: requires-dist
Dynamic: requires-python
Dynamic: summary
